mcp_server_google_vision/__init__.py
mcp_server_google_vision/__main__.py
mcp_server_google_vision/server.py
mcp_server_google_vision-1.0.0.dist-info/METADATA
mcp_server_google_vision-1.0.0.dist-info/WHEEL
mcp_server_google_vision-1.0.0.dist-info/entry_points.txt
mcp_server_google_vision-1.0.0.dist-info/licenses/LICENSE
mcp_server_google_vision-1.0.0.dist-info/RECORD
