Metadata-Version: 2.4
Name: mcp-server-google-vision
Version: 1.0.0
Summary: MCP server providing OCR capabilities to LLMs via Google Cloud Vision API - Read scanned PDFs, handwritten text, and images
Project-URL: Homepage, https://kohenavocats.com
Project-URL: Documentation, https://github.com/KohenAvocats/mcp-server-google-vision#readme
Project-URL: Repository, https://github.com/KohenAvocats/mcp-server-google-vision
Project-URL: Issues, https://github.com/KohenAvocats/mcp-server-google-vision/issues
Project-URL: Author, https://kohenavocats.com/avocat-hassan-kohen/
Author-email: Hassan Kohen <contact@kohenavocats.com>
Maintainer-email: Hassan Kohen <contact@kohenavocats.com>
License: MIT
License-File: LICENSE
Keywords: anthropic,claude,document-processing,google-vision,handwriting,legal-tech,llm,mcp,model-context-protocol,ocr,pdf
Classifier: Development Status :: 5 - Production/Stable
Classifier: Intended Audience :: Developers
Classifier: Intended Audience :: Legal Industry
Classifier: License :: OSI Approved :: MIT License
Classifier: Operating System :: OS Independent
Classifier: Programming Language :: Python :: 3
Classifier: Programming Language :: Python :: 3.11
Classifier: Programming Language :: Python :: 3.12
Classifier: Topic :: Scientific/Engineering :: Artificial Intelligence
Classifier: Topic :: Scientific/Engineering :: Image Recognition
Classifier: Topic :: Text Processing :: General
Requires-Python: >=3.11
Requires-Dist: aiohttp>=3.9.0
Requires-Dist: mcp[cli]>=1.6.0
